xmesh/__init__.py
xmesh/main.py
xmesh-0.4.1.dist-info/LICENSE
xmesh-0.4.1.dist-info/METADATA
xmesh-0.4.1.dist-info/WHEEL
xmesh-0.4.1.dist-info/entry_points.txt
xmesh-0.4.1.dist-info/top_level.txt
xmesh-0.4.1.dist-info/RECORD
