Metadata-Version: 2.1
Name: xmesh
Version: 0.4.1
Summary: xMesh sniffer.
Home-page: https://github.com/smartsnow/xmesh
Author: Snow Yang
Author-email: snowyang.iot@outlook.com
Project-URL: Bug Tracker, https://github.com/smartsnow/xmesh/issues
Classifier: Programming Language :: Python :: 3
Classifier: License :: OSI Approved :: MIT License
Classifier: Operating System :: OS Independent
Requires-Python: >=3.6
License-File: LICENSE
Requires-Dist: pyserial
Requires-Dist: rich
